odoo/addons/account_receipt_print/README.rst
odoo/addons/account_receipt_print/__init__.py
odoo/addons/account_receipt_print/__manifest__.py
odoo/addons/account_receipt_print/i18n/account_receipt_print.pot
odoo/addons/account_receipt_print/i18n/it.po
odoo/addons/account_receipt_print/models/__init__.py
odoo/addons/account_receipt_print/models/ir_actions_report.py
odoo/addons/account_receipt_print/readme/CONFIGURE.rst
odoo/addons/account_receipt_print/readme/CONTRIBUTORS.rst
odoo/addons/account_receipt_print/readme/DESCRIPTION.rst
odoo/addons/account_receipt_print/static/description/icon.png
odoo/addons/account_receipt_print/static/description/index.html
odoo/addons/account_receipt_print/views/account_report.xml
odoo/addons/account_receipt_print/views/report_receipt.xml
odoo14_addon_account_receipt_print-14.0.1.0.1.dist-info/METADATA
odoo14_addon_account_receipt_print-14.0.1.0.1.dist-info/WHEEL
odoo14_addon_account_receipt_print-14.0.1.0.1.dist-info/top_level.txt
odoo14_addon_account_receipt_print-14.0.1.0.1.dist-info/RECORD
